skheros/__init__.py
skheros/heros.py
skheros/methods/data_mange.py
skheros/methods/feature_tracking.py
skheros/methods/model.py
skheros/methods/model_feature_tracking.py
skheros/methods/model_population.py
skheros/methods/model_prediction.py
skheros/methods/rule.py
skheros/methods/rule_compaction.py
skheros/methods/rule_pareto_fitness.py
skheros/methods/rule_population.py
skheros/methods/rule_prediction.py
skheros/methods/rule_tracking.py
skheros/methods/time_tracking.py
skheros-0.2.5.dist-info/licenses/LICENSE
skheros-0.2.5.dist-info/METADATA
skheros-0.2.5.dist-info/WHEEL
skheros-0.2.5.dist-info/top_level.txt
skheros-0.2.5.dist-info/RECORD
