Metadata-Version: 2.4
Name: skheros
Version: 0.2.5
Summary: The Heuristic Evolutionary Rule Optimization System (HEROS) is a supervised rule-based machine learning algorithm designed to agnostically model diverse 'structured' data problems and yield compact human interpretable solutions. This implementation is scikit-learn compatible.
Author-email: Ryan Urbanowicz <ryanurbanowicz@gmail.com>
License: ACADEMIC SOFTWARE LICENSE
Project-URL: Source Code, https://github.com/UrbsLab/heros
Keywords: machine learning,rule-based,scikit-learn,interpretable,classification,supervised learning,evolutionary computation
Classifier: Intended Audience :: Science/Research
Classifier: Programming Language :: Python :: 3
Classifier: Programming Language :: Python :: 3.8
Classifier: Programming Language :: Python :: 3.9
Classifier: Programming Language :: Python :: 3.10
Classifier: Programming Language :: Python :: 3.11
Classifier: Programming Language :: Python :: 3.12
Classifier: Topic :: Scientific/Engineering :: Artificial Intelligence
Classifier: License :: Other/Proprietary License
Classifier: Operating System :: OS Independent
Requires-Python: >=3.8
License-File: LICENSE
Requires-Dist: numpy
Requires-Dist: pandas
Requires-Dist: scikit-learn
Requires-Dist: matplotlib
Requires-Dist: seaborn
Requires-Dist: scipy
Requires-Dist: skrebate==0.7
Requires-Dist: networkx
Provides-Extra: test
Requires-Dist: pytest>=7.0; extra == "test"
Requires-Dist: pytest-cov; extra == "test"
Requires-Dist: pytest-mock; extra == "test"
Requires-Dist: flake8; extra == "test"
Requires-Dist: mypy; extra == "test"
Dynamic: license-file
